{
	"isOptBtns":true,
	"columns":[
		{
			"prop":"financingNo",
			"isAutoWidth":true,
			"width":"",
			"minWidth":"",
			"perm":"",
			"isShow":true,
			"href":{
				"path":"",
				"query":"",
				"callbackType":"query"
			},
			"fixedColumn":false,
			"isHref":true,
			"fixed":"",
			"align":"left",
			"show-overflow-tooltip":true,
			"isQuery":false,
			"queryType":"2",
			"queryTableAlias":"",
			"value":"",
			"rules":[],
			"events":[],
			"state":[],
			"useState":"",
			"disableEdit":false,
			"openSort":false,
			"sort":"",
			"lazy":false,
			"sortType":"",
			"fieldType":"text",
			"dataType":"",
			"label":"融资编号",
			"formatter":"",
			"desensitization":"",
			"desensitizationFront":"",
			"desensitizationAfter":""
		},
		{
			"prop":"financingAmt",
			"isAutoWidth":true,
			"width":"",
			"minWidth":"",
			"perm":"",
			"isShow":true,
			"href":{
				"path":"",
				"query":"",
				"callbackType":"query"
			},
			"fixedColumn":false,
			"isHref":false,
			"fixed":"",
			"align":"left",
			"show-overflow-tooltip":false,
			"isQuery":false,
			"queryType":"2",
			"queryTableAlias":"",
			"value":"",
			"rules":[],
			"events":[],
			"state":[],
			"useState":"",
			"disableEdit":false,
			"openSort":false,
			"sort":"",
			"lazy":false,
			"sortType":"",
			"fieldType":"text",
			"dataType":"money(wan)",
			"label":"融资金额（万元）",
			"formatter":"",
			"desensitization":"",
			"desensitizationFront":"",
			"desensitizationAfter":""
		},
		{
			"prop":"financingType",
			"isAutoWidth":true,
			"width":"",
			"minWidth":"",
			"perm":"",
			"isShow":true,
			"href":{
				"path":"",
				"query":"",
				"callbackType":""
			},
			"fixedColumn":false,
			"isHref":false,
			"fixed":"",
			"align":"left",
			"show-overflow-tooltip":false,
			"isQuery":false,
			"queryType":"2",
			"queryTableAlias":"",
			"value":"",
			"rules":[],
			"events":[],
			"state":[],
			"useState":"",
			"disableEdit":false,
			"openSort":false,
			"sort":"",
			"lazy":false,
			"sortType":"",
			"fieldType":"select",
			"dataType":"",
			"label":"融资方式",
			"optionType":"2",
			"library":{
				"showField":"",
				"url":"",
				"realField":""
			},
			"dicKey":"INVESTMENT_PROPOSED_FINANCING_WAY",
			"dicItem":[
				{
					"optName":"债券",
					"optCode":"1"
				},
				{
					"optName":"发债",
					"optCode":"2"
				}
			]
		},
		{
			"prop":"startDate",
			"isAutoWidth":true,
			"width":"",
			"minWidth":"",
			"perm":"",
			"isShow":true,
			"href":{
				"path":"",
				"query":"",
				"callbackType":""
			},
			"fixedColumn":false,
			"isHref":false,
			"fixed":"",
			"align":"left",
			"show-overflow-tooltip":false,
			"isQuery":false,
			"queryType":"2",
			"queryTableAlias":"",
			"value":"",
			"rules":[],
			"events":[],
			"state":[],
			"useState":"",
			"disableEdit":false,
			"openSort":false,
			"sort":"",
			"lazy":false,
			"sortType":"",
			"fieldType":"date",
			"dataType":"",
			"label":"启动时间",
			"dateFormat":{
				"format":"yyyy-MM-dd",
				"valueFormat":"yyyyMMdd"
			},
			"dateOption":{
				"isLong":false,
				"bigDate":"",
				"defaultSmall":false,
				"smallDate":"",
				"defaultBig":false
			},
			"isBetween":false,
			"separator":"至",
			"placeholder":"开始日期",
			"endPlaceholder":"结束日期"
		},
		{
			"prop":"applyDate",
			"isAutoWidth":true,
			"width":"",
			"minWidth":"",
			"perm":"",
			"isShow":true,
			"href":{
				"path":"",
				"query":"",
				"callbackType":""
			},
			"fixedColumn":false,
			"isHref":false,
			"fixed":"",
			"align":"left",
			"show-overflow-tooltip":false,
			"isQuery":false,
			"queryType":"2",
			"queryTableAlias":"",
			"value":"",
			"rules":[],
			"events":[],
			"state":[],
			"useState":"",
			"disableEdit":false,
			"openSort":false,
			"sort":"",
			"lazy":false,
			"sortType":"",
			"fieldType":"date",
			"dataType":"",
			"label":"申请日期",
			"dateFormat":{
				"format":"yyyy-MM-dd",
				"valueFormat":"yyyyMMdd"
			},
			"dateOption":{
				"isLong":false,
				"bigDate":"",
				"defaultSmall":false,
				"smallDate":"",
				"defaultBig":false
			},
			"isBetween":false,
			"separator":"至",
			"placeholder":"开始日期",
			"endPlaceholder":"结束日期"
		},
		{
			"prop":"applyUserName",
			"isAutoWidth":true,
			"width":"",
			"minWidth":"",
			"perm":"",
			"isShow":true,
			"href":{
				"path":"",
				"query":"",
				"callbackType":""
			},
			"fixedColumn":false,
			"isHref":false,
			"fixed":"",
			"align":"left",
			"show-overflow-tooltip":false,
			"isQuery":false,
			"queryType":"2",
			"queryTableAlias":"",
			"value":"",
			"rules":[],
			"events":[],
			"state":[],
			"useState":"",
			"disableEdit":false,
			"openSort":false,
			"sort":"",
			"lazy":false,
			"sortType":"",
			"fieldType":"text",
			"dataType":"",
			"label":"申请人",
			"formatter":"",
			"desensitization":"",
			"desensitizationFront":"",
			"desensitizationAfter":""
		},
		{
			"prop":"applyOrgName",
			"isAutoWidth":true,
			"width":"",
			"minWidth":"",
			"perm":"",
			"isShow":true,
			"href":{
				"path":"",
				"query":"",
				"callbackType":""
			},
			"fixedColumn":false,
			"isHref":false,
			"fixed":"",
			"align":"left",
			"show-overflow-tooltip":false,
			"isQuery":false,
			"queryType":"2",
			"queryTableAlias":"",
			"value":"",
			"rules":[],
			"events":[],
			"state":[],
			"useState":"",
			"disableEdit":false,
			"openSort":false,
			"sort":"",
			"lazy":false,
			"sortType":"",
			"fieldType":"text",
			"dataType":"",
			"label":"申请部门",
			"formatter":"",
			"desensitization":"",
			"desensitizationFront":"",
			"desensitizationAfter":""
		},
		{
			"prop":"term",
			"isAutoWidth":true,
			"width":"",
			"minWidth":"",
			"perm":"",
			"isShow":true,
			"href":{
				"path":"",
				"query":"",
				"callbackType":""
			},
			"fixedColumn":false,
			"isHref":false,
			"fixed":"",
			"align":"left",
			"show-overflow-tooltip":false,
			"isQuery":false,
			"queryType":"2",
			"queryTableAlias":"",
			"value":"",
			"rules":[],
			"events":[],
			"state":[],
			"useState":"",
			"disableEdit":false,
			"openSort":false,
			"sort":"",
			"lazy":false,
			"sortType":"",
			"fieldType":"text",
			"dataType":"",
			"label":"期限",
			"formatter":"",
			"desensitization":"",
			"desensitizationFront":"",
			"desensitizationAfter":""
		},
		{
			"prop":"termType",
			"isAutoWidth":true,
			"width":"",
			"minWidth":"",
			"perm":"",
			"isShow":true,
			"href":{
				"path":"",
				"query":"",
				"callbackType":""
			},
			"fixedColumn":false,
			"isHref":false,
			"fixed":"",
			"align":"left",
			"show-overflow-tooltip":false,
			"isQuery":false,
			"queryType":"2",
			"queryTableAlias":"",
			"value":"",
			"rules":[],
			"events":[],
			"state":[],
			"useState":"",
			"disableEdit":false,
			"openSort":false,
			"sort":"",
			"lazy":false,
			"sortType":"",
			"fieldType":"select",
			"dataType":"",
			"label":"期限类型",
			"optionType":"2",
			"library":{
				"url":"",
				"realField":"",
				"showField":""
			},
			"dicKey":"INVESTMENT_CYCLE_TYPE",
			"dicItem":[]
		}
	],
	"tableName":"融资计划表",
	"isDynamicQuery":true,
	"isDColumn":true,
	"customBtns":[
		{
			"perm":"",
			"noShowParams":"",
			"prop":"opt_insert",
			"callback":"insert",
			"label":"新增",
			"fieldType":"customBtn"
		}
	],
	"paginationPageSize":10,
	"optBtns":[
		{
			"perm":"",
			"prop":"optBtn_1632382182151",
			"noShowParams":"",
			"callback":"showApprove",
			"label":"提款申请",
			"fieldType":"optBtn"
		}
	],
	"height":"auto",
	"isPagination":true,
	"query":"null",
	"isExport":false,
	"summationAddr":"front",
	"isSelect":false,
	"tableData":[],
	"modelType":"dynamicModel",
	"queryTabs":[],
	"dynamicQuery":{
		"prop":"dynamicQueryProp",
		"fieldNames":[
			"financingAmt"
		],
		"fieldType":"dynamicQuery"
	},
	"summationName":"合计",
	"url":"/mftcc-investment-server/group/busCliquesFinancingSchedule/findByPage",
	"isLoading":true,
	"isCustomQuery":false,
	"isBtnAutoWidth":true,
	"pageInfoClass":"isPagination",
	"tabActiveName":"0",
	"tableId":"busFinancingScheduleTable",
	"summationType":"currentSum",
	"searchColCut":2,
	"isAutoHeight":true
}