{
	"isOptBtns":true,
	"columns":[
		{
			"prop":"calcType",
			"isAutoWidth":true,
			"width":"",
			"minWidth":"",
			"perm":"",
			"isShow":true,
			"href":{
				"path":"",
				"query":"",
				"callbackType":"query"
			},
			"fixedColumn":false,
			"isHref":false,
			"fixed":"",
			"align":"left",
			"show-overflow-tooltip":false,
			"isQuery":false,
			"queryType":"2",
			"queryTableAlias":"",
			"value":"",
			"rules":[],
			"events":[],
			"state":[],
			"useState":"",
			"disableEdit":false,
			"openSort":false,
			"sort":"",
			"lazy":false,
			"sortType":"",
			"fieldType":"select",
			"dataType":"",
			"label":"计算参数",
			"optionType":"2",
			"library":{
				"showField":"",
				"url":"",
				"realField":""
			},
			"dicKey":"PRODUCT_CALC_TYPE",
			"dicItem":[]
		},
		{
			"prop":"overDaysFlag",
			"isAutoWidth":true,
			"width":"",
			"minWidth":"",
			"perm":"",
			"isShow":true,
			"href":{
				"path":"",
				"query":"",
				"callbackType":""
			},
			"fixedColumn":false,
			"isHref":false,
			"fixed":"",
			"align":"left",
			"show-overflow-tooltip":false,
			"isQuery":false,
			"queryType":"2",
			"queryTableAlias":"",
			"value":"",
			"rules":[],
			"events":[],
			"state":[],
			"useState":"",
			"disableEdit":false,
			"openSort":false,
			"sort":"",
			"lazy":false,
			"sortType":"",
			"fieldType":"select",
			"dataType":"",
			"label":"逾期天数计算",
			"optionType":"2",
			"library":{
				"showField":"",
				"url":"",
				"realField":""
			},
			"dicKey":"PRODUCT_OVER_DAYS_FLAG",
			"dicItem":[]
		},
		{
			"prop":"calcBaseDesc",
			"isAutoWidth":true,
			"width":"",
			"minWidth":"",
			"perm":"",
			"isShow":true,
			"href":{
				"path":"",
				"query":"",
				"callbackType":""
			},
			"fixedColumn":false,
			"isHref":false,
			"fixed":"",
			"align":"left",
			"show-overflow-tooltip":false,
			"isQuery":false,
			"queryType":"2",
			"queryTableAlias":"",
			"value":"",
			"rules":[],
			"events":[],
			"state":[],
			"useState":"",
			"disableEdit":false,
			"openSort":false,
			"sort":"",
			"lazy":false,
			"sortType":"",
			"fieldType":"text",
			"dataType":"",
			"label":"计算基数",
			"formatter":"",
			"desensitization":""
		}
	],
	"tableName":"核算参数计算方案",
	"isDynamicQuery":false,
	"isDColumn":true,
	"customBtns":[],
	"optBtns":[
		{
			"perm":"",
			"noShowParams":"",
			"prop":"opt_dit",
			"callback":"edit",
			"label":"修改",
			"fieldType":"optBtn"
		},
		{
			"perm":"",
			"noShowParams":"",
			"prop":"opt_delete",
			"callback":"delete",
			"label":"删除",
			"fieldType":"optBtn"
		}
	],
	"height":"auto",
	"isPagination":true,
	"query":"query",
	"isExport":false,
	"isSelect":false,
	"tableData":[],
	"modelType":"nothingModel",
	"queryTabs":[],
	"dynamicQuery":{
		"prop":"dynamicQueryProp",
		"fieldNames":[
			"calcType"
		],
		"fieldType":"dynamicQuery"
	},
	"url":"/mftcc-product-server/formulascheme/productCalcFormulaScheme/findProductByPage",
	"isLoading":true,
	"isCustomQuery":false,
	"isBtnAutoWidth":true,
	"pageInfoClass":"isPagination",
	"tabActiveName":"",
	"tableId":"productEditCalcFormulaTable",
	"searchColCut":2,
	"isAutoHeight":true
}