{
  "formId": "cusEvalIndexDetailsForm",
  "formName": "cusEvalIndexDetailsForm",
  "formDisabled": true,
  "labelPosition": "right",
  "query":"null",
  "columns": 2,
  "formItem": [
    {
      "label": "指标编号",
      "fieldName": "indexId",
      "fieldType": "text",
      "dataType": "",
      "value": "",
      "placeholder": "请输入指标编号",
      "readOnly": false,
      "disabled": true,
      "isShow": true,
      "rules":[
        {"type": "required", "message": "指标编号不能为空", "trigger": "blur"}
      ],
      "events":[],
      "colspan":1,
      "rowspan":1,
      "colIndex":"0",
          "rowIndex":0,
      "state":[],
      "useState": "",
      "suffix":"",
      "maxlength":"",
      "show-word-limit":false
    },
    {
      "label": "指标标识",
      "fieldName": "indexMark",
      "fieldType": "text",
      "dataType": "",
      "value": "",
      "placeholder": "请输入指标标识",
      "readOnly": false,
      "disabled": false,
      "isShow": true,
      "rules":[
        {"type": "required", "message": "指标标识不能为空", "trigger": "blur"}
      ],
      "events":[],
      "colspan":1,
      "rowspan":1,
      "colIndex":"1",
          "rowIndex":0,
      "state":[],
      "useState": "",
      "suffix":"",
      "maxlength":"",
      "show-word-limit":false
    },
    {
      "label": "指标名称",
      "fieldName": "indexName",
      "fieldType": "text",
      "dataType": "",
      "value": "",
      "placeholder": "请输入指标名称",
      "readOnly": false,
      "disabled": false,
      "isShow": true,
      "rules":[
        {"type": "required", "message": "指标名称不能为空", "trigger": "blur"}
      ],
      "events":[],
      "colspan":1,
      "rowspan":1,
      "colIndex":"0",
          "rowIndex":1,
      "state":[],
      "useState": "",
      "suffix":"",
      "maxlength":"",
      "show-word-limit":false
    },
    {
      "label": "指标取值来源1-财务指标2-sql查询3-java计算项",
      "fieldName": "sourceType",
      "fieldType": "text",
      "dataType": "",
      "value": "",
      "placeholder": "请输入指标取值来源1-财务指标2-sql查询3-java计算项",
      "readOnly": false,
      "disabled": false,
      "isShow": true,
      "rules":[
        {"type": "required", "message": "指标取值来源1-财务指标2-sql查询3-java计算项不能为空", "trigger": "blur"}
      ],
      "events":[],
      "colspan":1,
      "rowspan":1,
      "colIndex":"1",
          "rowIndex":1,
      "state":[],
      "useState": "",
      "suffix":"",
      "maxlength":"",
      "show-word-limit":false
    },
    {
      "label": "指标描述",
      "fieldName": "indexDesc",
      "fieldType": "text",
      "dataType": "",
      "value": "",
      "placeholder": "请输入指标描述",
      "readOnly": false,
      "disabled": false,
      "isShow": true,
      "rules":[
        {"type": "required", "message": "指标描述不能为空", "trigger": "blur"}
      ],
      "events":[],
      "colspan":1,
      "rowspan":1,
      "colIndex":"0",
          "rowIndex":2,
      "state":[],
      "useState": "",
      "suffix":"",
      "maxlength":"",
      "show-word-limit":false
    },
    {
      "label": "是否启用",
      "fieldName": "useFlag",
      "fieldType": "text",
      "dataType": "",
      "value": "",
      "placeholder": "请输入是否启用",
      "readOnly": false,
      "disabled": false,
      "isShow": true,
      "rules":[
        {"type": "required", "message": "是否启用不能为空", "trigger": "blur"}
      ],
      "events":[],
      "colspan":1,
      "rowspan":1,
      "colIndex":"1",
          "rowIndex":2,
      "state":[],
      "useState": "",
      "suffix":"",
      "maxlength":"",
      "show-word-limit":false
    },
    {
      "label": "关联指标名称 财务指标名/表单项名",
      "fieldName": "relIndexName",
      "fieldType": "text",
      "dataType": "",
      "value": "",
      "placeholder": "请输入关联指标名称 财务指标名/表单项名",
      "readOnly": false,
      "disabled": false,
      "isShow": true,
      "rules":[
        {"type": "required", "message": "关联指标名称 财务指标名/表单项名不能为空", "trigger": "blur"}
      ],
      "events":[],
      "colspan":1,
      "rowspan":1,
      "colIndex":"0",
          "rowIndex":3,
      "state":[],
      "useState": "",
      "suffix":"",
      "maxlength":"",
      "show-word-limit":false
    },
    {
      "label": "数据来源及描述 数据来源、计算公式描述、java类型",
      "fieldName": "dataSource",
      "fieldType": "text",
      "dataType": "",
      "value": "",
      "placeholder": "请输入数据来源及描述 数据来源、计算公式描述、java类型",
      "readOnly": false,
      "disabled": false,
      "isShow": true,
      "rules":[
        {"type": "required", "message": "数据来源及描述 数据来源、计算公式描述、java类型不能为空", "trigger": "blur"}
      ],
      "events":[],
      "colspan":1,
      "rowspan":1,
      "colIndex":"1",
          "rowIndex":3,
      "state":[],
      "useState": "",
      "suffix":"",
      "maxlength":"",
      "show-word-limit":false
    },
    {
      "label": "指标类型1财务评分2定量评分3定性评分",
      "fieldName": "indexType",
      "fieldType": "text",
      "dataType": "",
      "value": "",
      "placeholder": "请输入指标类型1财务评分2定量评分3定性评分",
      "readOnly": false,
      "disabled": false,
      "isShow": true,
      "rules":[
        {"type": "required", "message": "指标类型1财务评分2定量评分3定性评分不能为空", "trigger": "blur"}
      ],
      "events":[],
      "colspan":1,
      "rowspan":1,
      "colIndex":"0",
          "rowIndex":4,
      "state":[],
      "useState": "",
      "suffix":"",
      "maxlength":"",
      "show-word-limit":false
    },
    {
      "label": "权重比例",
      "fieldName": "weightRate",
      "fieldType": "text",
      "dataType": "double(6)",
      "value": "",
      "placeholder": "请输入权重比例",
      "readOnly": false,
      "disabled": false,
      "isShow": true,
      "rules":[
        {"type": "required", "message": "权重比例不能为空", "trigger": "blur"}
      ],
      "events":[],
      "colspan":1,
      "rowspan":1,
      "colIndex":"1",
          "rowIndex":4,
      "state":[],
      "useState": "",
      "suffix":"",
      "maxlength":"",
      "show-word-limit":false
    },
    {
      "label": "指标分值下限",
      "fieldName": "minScore",
      "fieldType": "text",
      "dataType": "double(6)",
      "value": "",
      "placeholder": "请输入指标分值下限",
      "readOnly": false,
      "disabled": false,
      "isShow": true,
      "rules":[
        {"type": "required", "message": "指标分值下限不能为空", "trigger": "blur"}
      ],
      "events":[],
      "colspan":1,
      "rowspan":1,
      "colIndex":"0",
          "rowIndex":5,
      "state":[],
      "useState": "",
      "suffix":"",
      "maxlength":"",
      "show-word-limit":false
    },
    {
      "label": "指标分值上限",
      "fieldName": "maxScore",
      "fieldType": "text",
      "dataType": "double(6)",
      "value": "",
      "placeholder": "请输入指标分值上限",
      "readOnly": false,
      "disabled": false,
      "isShow": true,
      "rules":[
        {"type": "required", "message": "指标分值上限不能为空", "trigger": "blur"}
      ],
      "events":[],
      "colspan":1,
      "rowspan":1,
      "colIndex":"1",
          "rowIndex":5,
      "state":[],
      "useState": "",
      "suffix":"",
      "maxlength":"",
      "show-word-limit":false
    },
    {
      "label": "得分规则1-获取当前档位最低分；2-获取当前档位最高分；3-java计算得分（该指标使用java取值时自动出分）",
      "fieldName": "scoreRules",
      "fieldType": "text",
      "dataType": "",
      "value": "",
      "placeholder": "请输入得分规则1-获取当前档位最低分；2-获取当前档位最高分；3-java计算得分（该指标使用java取值时自动出分）",
      "readOnly": false,
      "disabled": false,
      "isShow": true,
      "rules":[
        {"type": "required", "message": "得分规则1-获取当前档位最低分；2-获取当前档位最高分；3-java计算得分（该指标使用java取值时自动出分）不能为空", "trigger": "blur"}
      ],
      "events":[],
      "colspan":1,
      "rowspan":1,
      "colIndex":"0",
          "rowIndex":6,
      "state":[],
      "useState": "",
      "suffix":"",
      "maxlength":"",
      "show-word-limit":false
    },
    {
      "label": "分值是否允许修改0-否；1-是",
      "fieldName": "scoreEditFlag",
      "fieldType": "text",
      "dataType": "",
      "value": "",
      "placeholder": "请输入分值是否允许修改0-否；1-是",
      "readOnly": false,
      "disabled": false,
      "isShow": true,
      "rules":[
        {"type": "required", "message": "分值是否允许修改0-否；1-是不能为空", "trigger": "blur"}
      ],
      "events":[],
      "colspan":1,
      "rowspan":1,
      "colIndex":"1",
          "rowIndex":6,
      "state":[],
      "useState": "",
      "suffix":"",
      "maxlength":"",
      "show-word-limit":false
    },
    {
      "label": "法人机构编号",
      "fieldName": "corpId",
      "fieldType": "text",
      "dataType": "",
      "value": "",
      "placeholder": "请输入法人机构编号",
      "readOnly": false,
      "disabled": false,
      "isShow": true,
      "rules":[
        {"type": "required", "message": "法人机构编号不能为空", "trigger": "blur"}
      ],
      "events":[],
      "colspan":1,
      "rowspan":1,
      "colIndex":"0",
          "rowIndex":7,
      "state":[],
      "useState": "",
      "suffix":"",
      "maxlength":"",
      "show-word-limit":false
    },
    {
      "label": "法人机构名称",
      "fieldName": "corpName",
      "fieldType": "text",
      "dataType": "",
      "value": "",
      "placeholder": "请输入法人机构名称",
      "readOnly": false,
      "disabled": false,
      "isShow": true,
      "rules":[
        {"type": "required", "message": "法人机构名称不能为空", "trigger": "blur"}
      ],
      "events":[],
      "colspan":1,
      "rowspan":1,
      "colIndex":"1",
          "rowIndex":7,
      "state":[],
      "useState": "",
      "suffix":"",
      "maxlength":"",
      "show-word-limit":false
    }
  ]
}