{
	"isPagination":true,
	"isOptBtns":true,
	"columns":[
		{
			"prop":"impNo",
			"isAutoWidth":true,
			"width":"",
			"minWidth":"",
			"perm":"",
			"isShow":true,
			"href":{
				"path":"",
				"query":"",
				"callbackType":"query"
			},
			"fixedColumn":false,
			"isHref":true,
			"fixed":"",
			"align":"left",
			"show-overflow-tooltip":false,
			"isQuery":false,
			"queryType":"2",
			"queryTableAlias":"",
			"value":"",
			"rules":[],
			"events":[],
			"state":[],
			"useState":"",
			"disableEdit":false,
			"openSort":false,
			"sort":"",
			"lazy":false,
			"sortType":"",
			"fieldType":"text",
			"dataType":"",
			"label":"导入号",
			"formatter":"",
			"desensitization":""
		},
		{
			"prop":"regTime",
			"isAutoWidth":true,
			"width":"",
			"minWidth":"",
			"perm":"",
			"isShow":true,
			"href":{
				"path":"",
				"query":"",
				"callbackType":""
			},
			"fixedColumn":false,
			"isHref":false,
			"fixed":"",
			"align":"left",
			"show-overflow-tooltip":false,
			"isQuery":false,
			"queryType":"2",
			"queryTableAlias":"",
			"value":"",
			"rules":[],
			"events":[],
			"state":[],
			"useState":"",
			"disableEdit":false,
			"openSort":false,
			"sort":"descending",
			"lazy":false,
			"sortType":"defaultSort",
			"fieldType":"datetime",
			"dataType":"",
			"label":"导入时间",
			"dateFormat":{
				"format":"yyyy-MM-dd HH:mm:ss",
				"valueFormat":"yyyyMMdd HH:mm:ss"
			},
			"isBetween":false,
			"separator":"至",
			"placeholder":"开始日期",
			"endPlaceholder":"结束日期"
		},
		{
			"prop":"impFileName",
			"isAutoWidth":true,
			"width":"",
			"minWidth":"",
			"perm":"",
			"isShow":true,
			"href":{
				"path":"",
				"query":"",
				"callbackType":""
			},
			"fixedColumn":false,
			"isHref":false,
			"fixed":"",
			"align":"left",
			"show-overflow-tooltip":false,
			"isQuery":false,
			"queryType":"2",
			"queryTableAlias":"",
			"value":"",
			"rules":[],
			"events":[],
			"state":[],
			"useState":"",
			"disableEdit":false,
			"openSort":false,
			"sort":"",
			"lazy":false,
			"sortType":"",
			"fieldType":"text",
			"dataType":"",
			"label":"导入的文件名",
			"formatter":"",
			"desensitization":""
		},
		{
			"prop":"impOrigFileName",
			"isAutoWidth":true,
			"width":"",
			"minWidth":"",
			"perm":"",
			"isShow":true,
			"href":{
				"path":"",
				"query":"",
				"callbackType":""
			},
			"fixedColumn":false,
			"isHref":false,
			"fixed":"",
			"align":"left",
			"show-overflow-tooltip":false,
			"isQuery":false,
			"queryType":"2",
			"queryTableAlias":"",
			"value":"",
			"rules":[],
			"events":[],
			"state":[],
			"useState":"",
			"disableEdit":false,
			"openSort":false,
			"sort":"",
			"lazy":false,
			"sortType":"",
			"fieldType":"text",
			"dataType":"",
			"label":"导入的原始文件名",
			"formatter":"",
			"desensitization":""
		},
		{
			"prop":"impType",
			"isAutoWidth":true,
			"width":"",
			"minWidth":"",
			"perm":"",
			"isShow":true,
			"href":{
				"path":"",
				"query":"",
				"callbackType":""
			},
			"fixedColumn":false,
			"isHref":false,
			"fixed":"",
			"align":"left",
			"show-overflow-tooltip":false,
			"isQuery":false,
			"queryType":"2",
			"queryTableAlias":"",
			"value":"",
			"rules":[],
			"events":[],
			"state":[],
			"useState":"",
			"disableEdit":false,
			"openSort":false,
			"sort":"",
			"lazy":false,
			"sortType":"",
			"fieldType":"select",
			"dataType":"",
			"label":"导入类型",
			"optionType":"1",
			"library":{
				"showField":"",
				"url":"",
				"realField":""
			},
			"dicKey":"",
			"dicItem":[
				{
					"optName":"再担保",
					"optCode":"1"
				},
				{
					"optName":"代偿",
					"optCode":"2"
				}
			]
		},
		{
			"prop":"impSts",
			"isAutoWidth":true,
			"width":"",
			"minWidth":"",
			"perm":"",
			"isShow":true,
			"href":{
				"path":"",
				"query":"",
				"callbackType":""
			},
			"fixedColumn":false,
			"isHref":false,
			"fixed":"",
			"align":"left",
			"show-overflow-tooltip":false,
			"isQuery":false,
			"queryType":"2",
			"queryTableAlias":"",
			"value":"",
			"rules":[],
			"events":[],
			"state":[],
			"useState":"",
			"disableEdit":false,
			"openSort":false,
			"sort":"",
			"lazy":false,
			"sortType":"",
			"fieldType":"select",
			"dataType":"",
			"label":"导入状态",
			"optionType":"1",
			"library":{
				"showField":"",
				"url":"",
				"realField":""
			},
			"dicKey":"",
			"dicItem":[
				{
					"optName":"导入失败",
					"optCode":"1"
				},
				{
					"optName":"导入成功",
					"optCode":"2"
				}
			]
		}
	],
	"isExport":false,
	"isSelect":false,
	"tableData":[],
	"modelType":"dynamicModel",
	"queryTabs":[
		{
			"fieldName":"impType",
			"id":"tab_1628563672359",
			"label":"全部",
			"fieldType":"queryTab",
			"value":""
		},
		{
			"fieldName":"impType",
			"id":"tab_1628563708300",
			"label":"再担保",
			"fieldType":"queryTab",
			"value":"1"
		},
		{
			"fieldName":"impType",
			"id":"tab_1628564608687",
			"label":"代偿",
			"fieldType":"queryTab",
			"value":"2"
		}
	],
	"dynamicQuery":{
		"prop":"dynamicQueryProp",
		"fieldNames":[
			"impNo"
		],
		"fieldType":"dynamicQuery"
	},
	"url":"/mftcc-guarantee-server/record/guaranteeImportRecord/findByPage",
	"tableName":"历史数据导入记录表",
	"isLoading":true,
	"isDynamicQuery":true,
	"isCustomQuery":false,
	"isDColumn":true,
	"pageInfoClass":"isPagination",
	"tabActiveName":"tab_1628563672359",
	"tableId":"guaranteeImportRecordTable",
	"customBtns":[
		{
			"perm":"",
			"prop":"cusBtn_1628566447237",
			"noShowParams":"",
			"callback":"goBack",
			"label":"返回",
			"fieldType":"customBtn",
			"colorType":"primary"
		}
	],
	"optBtns":[
		{
			"perm":"",
			"noShowParams":"",
			"prop":"opt_dit",
			"callback":"downloadFile",
			"label":"下载文件",
			"fieldType":"optBtn",
			"colorType":"primary"
		},
		{
			"perm":"",
			"noShowParams":"",
			"prop":"opt_delete",
			"callback":"delete",
			"label":"删除",
			"fieldType":"optBtn"
		}
	],
	"searchColCut":2,
	"isAutoHeight":true,
	"height":"auto"
}