{
	"isPagination":true,
	"isOptBtns":true,
	"columns":[
		{
			"prop":"extensionNo",
			"isAutoWidth":true,
			"width":"",
			"minWidth":"",
			"perm":"",
			"isShow":true,
			"href":{
				"path":"",
				"query":"",
				"callbackType":"query"
			},
			"fixedColumn":false,
			"isHref":true,
			"fixed":"",
			"suffix":"",
			"align":"left",
			"show-overflow-tooltip":true,
			"isQuery":false,
			"queryType":"2",
			"queryTableAlias":"",
			"value":"",
			"rules":[],
			"events":[],
			"state":[],
			"useState":"",
			"disableEdit":false,
			"openSort":false,
			"sort":"",
			"lazy":false,
			"sortType":"",
			"fieldType":"text",
			"dataType":"",
			"label":"展期展示号",
			"formatter":"",
			"desensitization":"",
			"desensitizationFront":"",
			"desensitizationAfter":""
		},
		{
			"prop":"contractNo",
			"isAutoWidth":true,
			"width":"",
			"minWidth":"",
			"perm":"",
			"isShow":true,
			"href":{
				"path":"",
				"query":"",
				"callbackType":""
			},
			"fixedColumn":false,
			"isHref":false,
			"fixed":"",
			"suffix":"",
			"align":"left",
			"show-overflow-tooltip":true,
			"isQuery":false,
			"queryType":"2",
			"queryTableAlias":"",
			"value":"",
			"rules":[],
			"events":[],
			"state":[],
			"useState":"",
			"disableEdit":false,
			"openSort":false,
			"sort":"",
			"lazy":false,
			"sortType":"",
			"fieldType":"text",
			"dataType":"",
			"label":"合同展示号",
			"formatter":"",
			"desensitization":"",
			"desensitizationFront":"",
			"desensitizationAfter":""
		},
		{
			"prop":"subsidiaryName",
			"isAutoWidth":true,
			"width":"",
			"minWidth":"",
			"perm":"",
			"isShow":true,
			"href":{
				"path":"",
				"query":"",
				"callbackType":""
			},
			"fixedColumn":false,
			"isHref":false,
			"fixed":"",
			"suffix":"",
			"align":"left",
			"show-overflow-tooltip":true,
			"isQuery":false,
			"queryType":"2",
			"queryTableAlias":"",
			"value":"",
			"rules":[],
			"events":[],
			"state":[],
			"useState":"",
			"disableEdit":false,
			"openSort":false,
			"sort":"",
			"lazy":false,
			"sortType":"",
			"fieldType":"text",
			"dataType":"",
			"label":"借款公司名称",
			"formatter":"",
			"desensitization":"",
			"desensitizationFront":"",
			"desensitizationAfter":""
		},
		{
			"prop":"contacts",
			"isAutoWidth":true,
			"width":"",
			"minWidth":"",
			"perm":"",
			"isShow":true,
			"href":{
				"path":"",
				"query":"",
				"callbackType":""
			},
			"fixedColumn":false,
			"isHref":false,
			"fixed":"",
			"suffix":"",
			"align":"left",
			"show-overflow-tooltip":false,
			"isQuery":false,
			"queryType":"2",
			"queryTableAlias":"",
			"value":"",
			"rules":[],
			"events":[],
			"state":[],
			"useState":"",
			"disableEdit":false,
			"openSort":false,
			"sort":"",
			"lazy":false,
			"sortType":"",
			"fieldType":"text",
			"dataType":"",
			"label":"联系人",
			"formatter":"",
			"desensitization":"",
			"desensitizationFront":"",
			"desensitizationAfter":""
		},
		{
			"prop":"contactInformation",
			"isAutoWidth":true,
			"width":"",
			"minWidth":"",
			"perm":"",
			"isShow":true,
			"href":{
				"path":"",
				"query":"",
				"callbackType":""
			},
			"fixedColumn":false,
			"isHref":false,
			"fixed":"",
			"suffix":"",
			"align":"left",
			"show-overflow-tooltip":false,
			"isQuery":false,
			"queryType":"2",
			"queryTableAlias":"",
			"value":"",
			"rules":[],
			"events":[],
			"state":[],
			"useState":"",
			"disableEdit":false,
			"openSort":false,
			"sort":"",
			"lazy":false,
			"sortType":"",
			"fieldType":"text",
			"dataType":"",
			"label":"联系方式",
			"formatter":"",
			"desensitization":"",
			"desensitizationFront":"",
			"desensitizationAfter":""
		},
		{
			"prop":"projectName",
			"isAutoWidth":true,
			"width":"",
			"minWidth":"",
			"perm":"",
			"isShow":true,
			"href":{
				"path":"",
				"query":"",
				"callbackType":""
			},
			"fixedColumn":false,
			"isHref":false,
			"fixed":"",
			"suffix":"",
			"align":"left",
			"show-overflow-tooltip":false,
			"isQuery":false,
			"queryType":"2",
			"queryTableAlias":"",
			"value":"",
			"rules":[],
			"events":[],
			"state":[],
			"useState":"",
			"disableEdit":false,
			"openSort":false,
			"sort":"",
			"lazy":false,
			"sortType":"",
			"fieldType":"text",
			"dataType":"",
			"label":"项目名称",
			"formatter":"",
			"desensitization":"",
			"desensitizationFront":"",
			"desensitizationAfter":""
		},
		{
			"prop":"extensionAmt",
			"isAutoWidth":true,
			"width":"",
			"minWidth":"",
			"perm":"",
			"isShow":true,
			"href":{
				"path":"",
				"query":"",
				"callbackType":""
			},
			"fixedColumn":false,
			"isHref":false,
			"fixed":"",
			"suffix":"",
			"align":"left",
			"show-overflow-tooltip":false,
			"isQuery":false,
			"queryType":"2",
			"queryTableAlias":"",
			"value":"",
			"rules":[],
			"events":[],
			"state":[],
			"useState":"",
			"disableEdit":false,
			"openSort":false,
			"sort":"",
			"lazy":false,
			"sortType":"",
			"fieldType":"text",
			"dataType":"money(yuan)",
			"label":"展期金额",
			"formatter":"",
			"desensitization":"",
			"desensitizationFront":"",
			"desensitizationAfter":""
		},
		{
			"prop":"extensionSummary",
			"isAutoWidth":true,
			"width":"",
			"minWidth":"",
			"perm":"",
			"isShow":true,
			"href":{
				"path":"",
				"query":"",
				"callbackType":""
			},
			"fixedColumn":false,
			"isHref":false,
			"fixed":"",
			"suffix":"",
			"align":"left",
			"show-overflow-tooltip":false,
			"isQuery":false,
			"queryType":"2",
			"queryTableAlias":"",
			"value":"",
			"rules":[],
			"events":[],
			"state":[],
			"useState":"",
			"disableEdit":false,
			"openSort":false,
			"sort":"",
			"lazy":false,
			"sortType":"",
			"fieldType":"text",
			"dataType":"",
			"label":"展期原因",
			"formatter":"",
			"desensitization":"",
			"desensitizationFront":"",
			"desensitizationAfter":""
		}
	],
	"isExport":false,
	"isSelect":false,
	"tableData":[],
	"modelType":"dynamicModel",
	"queryTabs":[],
	"dynamicQuery":{
		"prop":"dynamicQueryProp",
		"fieldNames":[],
		"fieldType":"dynamicQuery"
	},
	"url":"/mftcc-investment-server/group/busCliquesLoanExtension/findByPage",
	"tableName":"借款展期",
	"isLoading":true,
	"isDynamicQuery":true,
	"isCustomQuery":false,
	"isDColumn":true,
	"pageInfoClass":"isPagination",
	"tabActiveName":"0",
	"tableId":"busCliquesLoanExtensionTable",
	"customBtns":[],
	"paginationPageSize":10,
	"optBtns":[
		{
			"perm":"",
			"noShowParams":"isExtension-0;",
			"prop":"opt_dit",
			"callback":"extctrInsert",
			"label":"展期合同",
			"fieldType":"optBtn"
		}
	],
	"searchColCut":2,
	"isAutoHeight":true,
	"height":"auto"
}