{
	"formId":"guaranteeImportRecordUpdateForm",
	"formItem":[
		{
			"label":"导入号",
			"fieldName":"impNo",
			"fieldType":"text",
			"dataType":"String",
			"value":"",
			"placeholder":"请输入导入号",
			"readOnly":false,
			"disabled":true,
			"isShow":true,
			"rules":[
				{
					"type":"required",
					"message":"导入号不能为空",
					"trigger":"blur"
				}
			],
			"events":[],
			"colspan":1,
			"rowspan":1,
			"colIndex":0,
			"rowIndex":0,
			"state":[],
			"useState":"",
			"menuType":"common",
			"showContents":1,
			"href":{
				"path":"",
				"query":"",
				"callbackType":""
			},
			"isHref":false,
			"optBtn":[],
			"suffix":"",
			"maxlength":"",
			"show-word-limit":false,
			"uuid":"w78bca331eb74742"
		},
		{
			"label":"导入时间",
			"fieldName":"regTime",
			"fieldType":"date",
			"dataType":"",
			"value":"",
			"placeholder":"请输入导入时间",
			"readOnly":false,
			"disabled":false,
			"isShow":true,
			"rules":[
				{
					"type":"required",
					"message":"导入时间不能为空",
					"trigger":"change"
				}
			],
			"events":[],
			"colspan":1,
			"rowspan":1,
			"colIndex":1,
			"rowIndex":0,
			"state":[],
			"useState":"",
			"menuType":"common",
			"showContents":1,
			"href":{
				"path":"",
				"query":"",
				"callbackType":""
			},
			"isHref":false,
			"optBtn":[],
			"dateFormat":{
				"format":"yyyy-MM-dd",
				"valueFormat":"yyyyMMdd"
			},
			"dateOption":{
				"isLong":false
			},
			"dateType":"date",
			"uuid":"w993b9f59e824efc"
		},
		{
			"label":"导入的文件名",
			"fieldName":"impFileName",
			"fieldType":"text",
			"dataType":"String",
			"value":"",
			"placeholder":"请输入导入的文件名",
			"readOnly":false,
			"disabled":false,
			"isShow":true,
			"rules":[
				{
					"type":"required",
					"message":"导入的文件名不能为空",
					"trigger":"blur"
				}
			],
			"events":[],
			"colspan":1,
			"rowspan":1,
			"colIndex":0,
			"rowIndex":1,
			"state":[],
			"useState":"",
			"menuType":"common",
			"showContents":1,
			"href":{
				"path":"",
				"query":"",
				"callbackType":""
			},
			"isHref":false,
			"optBtn":[],
			"suffix":"",
			"maxlength":"",
			"show-word-limit":false,
			"uuid":"w7c0ba3beaa2424a"
		},
		{
			"label":"导入的原始文件名",
			"fieldName":"impOrigFileName",
			"fieldType":"text",
			"dataType":"String",
			"value":"",
			"placeholder":"请输入导入的原始文件名",
			"readOnly":false,
			"disabled":false,
			"isShow":true,
			"rules":[
				{
					"type":"required",
					"message":"导入的原始文件名不能为空",
					"trigger":"blur"
				}
			],
			"events":[],
			"colspan":1,
			"rowspan":1,
			"colIndex":1,
			"rowIndex":1,
			"state":[],
			"useState":"",
			"menuType":"common",
			"showContents":1,
			"href":{
				"path":"",
				"query":"",
				"callbackType":""
			},
			"isHref":false,
			"optBtn":[],
			"suffix":"",
			"maxlength":"",
			"show-word-limit":false,
			"uuid":"w13dea2be587462c"
		},
		{
			"label":"导入类型",
			"fieldName":"impType",
			"fieldType":"select",
			"dataType":"String",
			"value":"",
			"placeholder":"请输入导入类型",
			"readOnly":false,
			"disabled":false,
			"isShow":true,
			"rules":[
				{
					"type":"required",
					"message":"导入类型(1-再担保,2-代偿)不能为空",
					"trigger":"change"
				}
			],
			"events":[],
			"colspan":1,
			"rowspan":1,
			"colIndex":0,
			"rowIndex":2,
			"state":[],
			"useState":"",
			"menuType":"common",
			"showContents":1,
			"href":{
				"path":"",
				"query":"",
				"callbackType":""
			},
			"isHref":false,
			"optBtn":[],
			"dicKey":"",
			"dicItem":[
				{
					"optCode":"1",
					"optName":"再担保"
				},
				{
					"optCode":"2",
					"optName":"代偿"
				}
			],
			"library":{},
			"uuid":"w707c9f33da640fa",
			"optionType":"1"
		},
		{
			"label":"导入状态",
			"fieldName":"impSts",
			"fieldType":"select",
			"dataType":"String",
			"value":"1",
			"placeholder":"请输入导入状态",
			"readOnly":true,
			"disabled":false,
			"isShow":true,
			"rules":[
				{
					"type":"required",
					"message":"导入状态 1-已上传，2-已导入不能为空",
					"trigger":"change"
				}
			],
			"events":[],
			"colspan":1,
			"rowspan":1,
			"colIndex":1,
			"rowIndex":2,
			"state":[],
			"useState":"",
			"menuType":"common",
			"showContents":1,
			"href":{
				"path":"",
				"query":"",
				"callbackType":""
			},
			"isHref":false,
			"optBtn":[],
			"dicKey":"",
			"dicItem":[
				{
					"optCode":"1",
					"optName":"导入失败"
				},
				{
					"optCode":"2",
					"optName":"导入成功"
				}
			],
			"library":{},
			"uuid":"we07f9fae79d4595",
			"optionType":"1"
		},
		{
			"label":"备注",
			"fieldName":"remark",
			"fieldType":"textarea",
			"dataType":"String",
			"value":"",
			"placeholder":"请输入备注",
			"readOnly":false,
			"disabled":false,
			"isShow":true,
			"rules":[],
			"events":[],
			"colspan":2,
			"rowspan":1,
			"colIndex":0,
			"rowIndex":3,
			"state":[],
			"useState":"",
			"menuType":"common",
			"showContents":1,
			"href":{
				"path":"",
				"query":"",
				"callbackType":""
			},
			"isHref":false,
			"optBtn":[],
			"suffix":"",
			"maxlength":"",
			"show-word-limit":false,
			"isAutoRows":false,
			"maxRows":6,
			"minRows":3,
			"uuid":"w66bfb2bf6ba4c45"
		},
		{
			"fieldType":"empty",
			"rowspan":0,
			"colspan":0,
			"rowIndex":3,
			"colIndex":1,
			"uuid":"w5d5595e3d964f26",
			"belong":"left"
		}
	],
	"labelPosition":"right",
	"columns":2,
	"formName":"guaranteeImportRecordUpdateForm",
	"query":"null",
	"formDisabled":false
}