{
	"formId":"guaranteeCollectConfirmUpdateForm",
	"formItem":[
		{
			"label":"项目名称",
			"fieldName":"applyName",
			"fieldType":"text",
			"dataType":"String",
			"value":"",
			"placeholder":"请输入项目名称",
			"readOnly":true,
			"disabled":false,
			"isShow":true,
			"rules":[
				{
					"trigger":"blur",
					"type":"required",
					"message":"项目名称不能为空"
				}
			],
			"events":[],
			"colspan":1,
			"rowspan":1,
			"colIndex":0,
			"rowIndex":0,
			"state":[],
			"useState":"",
			"menuType":"common",
			"showContents":1,
			"href":{
				"path":"",
				"query":"",
				"callbackType":""
			},
			"isHref":false,
			"optBtn":[],
			"suffix":"",
			"maxlength":"",
			"show-word-limit":false,
			"desensitization":"",
			"desensitizationFront":"",
			"desensitizationAfter":"",
			"isBigAmt":false,
			"uuid":"w5b3494eeeb34c2c"
		},
		{
			"label":"产品名称",
			"fieldName":"productName",
			"fieldType":"text",
			"dataType":"String",
			"value":"",
			"placeholder":"请输入产品名称",
			"readOnly":true,
			"disabled":false,
			"isShow":true,
			"rules":[
				{
					"trigger":"blur",
					"type":"required",
					"message":"产品名称不能为空"
				}
			],
			"events":[],
			"colspan":1,
			"rowspan":1,
			"colIndex":1,
			"rowIndex":0,
			"state":[],
			"useState":"",
			"menuType":"common",
			"showContents":1,
			"href":{
				"path":"",
				"query":"",
				"callbackType":""
			},
			"isHref":false,
			"optBtn":[],
			"suffix":"",
			"maxlength":"",
			"show-word-limit":false,
			"desensitization":"",
			"desensitizationFront":"",
			"desensitizationAfter":"",
			"isBigAmt":false,
			"uuid":"wda449b9c494430a"
		},
		{
			"label":"客户名称",
			"fieldName":"cusName",
			"fieldType":"text",
			"dataType":"String",
			"value":"",
			"placeholder":"请输入客户名称",
			"readOnly":true,
			"disabled":false,
			"isShow":true,
			"rules":[
				{
					"trigger":"blur",
					"type":"required",
					"message":"客户名称不能为空"
				}
			],
			"events":[],
			"colspan":1,
			"rowspan":1,
			"colIndex":0,
			"rowIndex":1,
			"state":[],
			"useState":"",
			"menuType":"common",
			"showContents":1,
			"href":{
				"path":"",
				"query":"",
				"callbackType":""
			},
			"isHref":false,
			"optBtn":[],
			"suffix":"",
			"maxlength":"",
			"show-word-limit":false,
			"desensitization":"",
			"desensitizationFront":"",
			"desensitizationAfter":"",
			"isBigAmt":false,
			"uuid":"w32dbbacdf9447f6"
		},
		{
			"fieldType":"empty",
			"rowspan":1,
			"colspan":1,
			"rowIndex":1,
			"colIndex":1,
			"uuid":"w32a1b9aecba4915"
		},
		{
			"label":"担保金额",
			"fieldName":"guaAmt",
			"fieldType":"text",
			"dataType":"money(yuan)",
			"value":"",
			"placeholder":"请输入担保金额",
			"readOnly":true,
			"disabled":false,
			"isShow":true,
			"rules":[
				{
					"type":"required",
					"message":"担保金额不能为空",
					"trigger":"blur"
				}
			],
			"events":[],
			"colspan":2,
			"rowspan":1,
			"colIndex":0,
			"rowIndex":2,
			"state":[],
			"useState":"",
			"menuType":"common",
			"showContents":1,
			"href":{
				"path":"",
				"query":"",
				"callbackType":""
			},
			"isHref":false,
			"optBtn":[],
			"suffix":"元",
			"maxlength":"",
			"show-word-limit":false,
			"desensitization":"",
			"desensitizationFront":"",
			"desensitizationAfter":"",
			"isBigAmt":true,
			"uuid":"wcb7088c55a442b8"
		},
		{
			"fieldType":"empty",
			"rowspan":0,
			"colspan":0,
			"rowIndex":2,
			"colIndex":1,
			"uuid":"w80d28a56c8746bb",
			"belong":"left"
		},
		{
			"label":"担保期限",
			"fieldName":"termShow",
			"fieldType":"text",
			"dataType":"",
			"value":"",
			"placeholder":"请输入担保期限",
			"readOnly":true,
			"disabled":false,
			"isShow":true,
			"rules":[
				{
					"trigger":"blur",
					"type":"required",
					"message":"担保期限不能为空"
				}
			],
			"events":[],
			"colspan":1,
			"rowspan":1,
			"colIndex":0,
			"rowIndex":3,
			"state":[],
			"useState":"",
			"menuType":"common",
			"showContents":1,
			"href":{
				"path":"",
				"query":"",
				"callbackType":""
			},
			"isHref":false,
			"optBtn":[],
			"suffix":"",
			"maxlength":"",
			"show-word-limit":false,
			"desensitization":"",
			"desensitizationFront":"",
			"desensitizationAfter":"",
			"isBigAmt":false,
			"uuid":"w947aad3379b4084"
		},
		{
			"colspan":1,
			"showContents":1,
			"rowspan":1,
			"colIndex":1,
			"rowIndex":3,
			"state":[],
			"fieldType":"empty",
			"uuid":"w76e5b634dab478f"
		},
		{
			"label":"应收担保费",
			"fieldName":"guaranteeAmt",
			"fieldType":"text",
			"dataType":"money(yuan)",
			"value":"",
			"placeholder":"请输入应收担保费",
			"readOnly":true,
			"disabled":false,
			"isShow":true,
			"rules":[],
			"events":[],
			"colspan":2,
			"rowspan":1,
			"colIndex":0,
			"rowIndex":4,
			"state":[],
			"useState":"",
			"menuType":"common",
			"showContents":1,
			"href":{
				"path":"",
				"query":"",
				"callbackType":""
			},
			"isHref":false,
			"optBtn":[],
			"suffix":"元",
			"maxlength":"",
			"show-word-limit":false,
			"desensitization":"",
			"desensitizationFront":"",
			"desensitizationAfter":"",
			"isBigAmt":true,
			"uuid":"w9e0c84c749c415a"
		},
		{
			"fieldType":"empty",
			"rowspan":0,
			"colspan":0,
			"rowIndex":4,
			"colIndex":1,
			"uuid":"wc4359299b8e4264",
			"belong":"left"
		},
		{
			"label":"应收服务费",
			"fieldName":"waiterAmt",
			"fieldType":"text",
			"dataType":"money(yuan)",
			"value":"",
			"placeholder":"请输入应收手续费",
			"readOnly":true,
			"disabled":false,
			"isShow":true,
			"rules":[],
			"events":[],
			"colspan":2,
			"rowspan":1,
			"colIndex":0,
			"rowIndex":5,
			"state":[],
			"useState":"",
			"menuType":"common",
			"showContents":1,
			"href":{
				"path":"",
				"query":"",
				"callbackType":""
			},
			"isHref":false,
			"optBtn":[],
			"suffix":"元",
			"maxlength":"",
			"show-word-limit":false,
			"desensitization":"",
			"desensitizationFront":"",
			"desensitizationAfter":"",
			"isBigAmt":true,
			"uuid":"we908b1300914b4f"
		},
		{
			"fieldType":"empty",
			"rowspan":0,
			"colspan":0,
			"rowIndex":5,
			"colIndex":1,
			"uuid":"w6b6995fc3bf46ec",
			"belong":"left"
		},
		{
			"label":"应收保证金",
			"fieldName":"bond",
			"fieldType":"text",
			"dataType":"money(yuan)",
			"value":"",
			"placeholder":"请输入应收保证金",
			"readOnly":true,
			"disabled":false,
			"isShow":true,
			"rules":[],
			"events":[],
			"colspan":2,
			"rowspan":1,
			"colIndex":0,
			"rowIndex":6,
			"state":[],
			"useState":"",
			"menuType":"common",
			"showContents":1,
			"href":{
				"path":"",
				"query":"",
				"callbackType":""
			},
			"isHref":false,
			"optBtn":[],
			"suffix":"元",
			"maxlength":"",
			"show-word-limit":false,
			"desensitization":"",
			"desensitizationFront":"",
			"desensitizationAfter":"",
			"isBigAmt":true,
			"uuid":"w87ab92165b242d6"
		},
		{
			"fieldType":"empty",
			"rowspan":0,
			"colspan":0,
			"rowIndex":6,
			"colIndex":1,
			"uuid":"wffaa980be994045",
			"belong":"left"
		},
		{
			"label":"应收金额",
			"fieldName":"receivableAmt",
			"fieldType":"text",
			"dataType":"money(yuan)",
			"value":"",
			"placeholder":"请输入应收金额",
			"readOnly":true,
			"disabled":false,
			"isShow":true,
			"rules":[],
			"events":[],
			"colspan":2,
			"rowspan":1,
			"colIndex":0,
			"rowIndex":7,
			"state":[],
			"useState":"",
			"menuType":"common",
			"showContents":1,
			"href":{
				"path":"",
				"query":"",
				"callbackType":""
			},
			"isHref":false,
			"optBtn":[],
			"suffix":"元",
			"maxlength":"",
			"show-word-limit":false,
			"desensitization":"",
			"desensitizationFront":"",
			"desensitizationAfter":"",
			"isBigAmt":true,
			"uuid":"w8712a0916854c0f"
		},
		{
			"fieldType":"empty",
			"rowspan":0,
			"colspan":0,
			"rowIndex":7,
			"colIndex":1,
			"uuid":"w4259b9a3cbc4bd7",
			"belong":"left"
		},
		{
			"label":"实收担保费",
			"fieldName":"actualGuaranteeAmt",
			"fieldType":"text",
			"dataType":"money(yuan)",
			"value":"",
			"placeholder":"请输入实收担保费",
			"readOnly":false,
			"disabled":false,
			"isShow":true,
			"rules":[],
			"events":[],
			"colspan":2,
			"rowspan":1,
			"colIndex":0,
			"rowIndex":8,
			"state":[],
			"useState":"",
			"menuType":"common",
			"showContents":1,
			"href":{
				"path":"",
				"query":"",
				"callbackType":""
			},
			"isHref":false,
			"optBtn":[],
			"suffix":"元",
			"maxlength":"",
			"show-word-limit":false,
			"desensitization":"",
			"desensitizationFront":"",
			"desensitizationAfter":"",
			"isBigAmt":true,
			"uuid":"w7491ad9da874bc3"
		},
		{
			"fieldType":"empty",
			"rowspan":0,
			"colspan":0,
			"rowIndex":8,
			"colIndex":1,
			"uuid":"wa6b2a6b4b8a4670",
			"belong":"left"
		},
		{
			"label":"实收服务费",
			"fieldName":"actualWaiterAmt",
			"fieldType":"text",
			"dataType":"money(yuan)",
			"value":"",
			"placeholder":"请输入实际手续费",
			"readOnly":false,
			"disabled":false,
			"isShow":true,
			"rules":[],
			"events":[],
			"colspan":2,
			"rowspan":1,
			"colIndex":0,
			"rowIndex":9,
			"state":[],
			"useState":"",
			"menuType":"common",
			"showContents":1,
			"href":{
				"path":"",
				"query":"",
				"callbackType":""
			},
			"isHref":false,
			"optBtn":[],
			"suffix":"元",
			"maxlength":"",
			"show-word-limit":false,
			"desensitization":"",
			"desensitizationFront":"",
			"desensitizationAfter":"",
			"isBigAmt":true,
			"uuid":"w446686710b64ed6"
		},
		{
			"fieldType":"empty",
			"rowspan":0,
			"colspan":0,
			"rowIndex":9,
			"colIndex":1,
			"uuid":"wb08d9953da14a34",
			"belong":"left"
		},
		{
			"label":"实收保证金",
			"fieldName":"actualBond",
			"fieldType":"text",
			"dataType":"money(yuan)",
			"value":"",
			"placeholder":"请输入实收保证金",
			"readOnly":false,
			"disabled":false,
			"isShow":true,
			"rules":[],
			"events":[],
			"colspan":2,
			"rowspan":1,
			"colIndex":0,
			"rowIndex":10,
			"state":[],
			"useState":"",
			"menuType":"common",
			"showContents":1,
			"href":{
				"path":"",
				"query":"",
				"callbackType":""
			},
			"isHref":false,
			"optBtn":[],
			"suffix":"元",
			"maxlength":"",
			"show-word-limit":false,
			"desensitization":"",
			"desensitizationFront":"",
			"desensitizationAfter":"",
			"isBigAmt":true,
			"uuid":"w421d9ae62884ae7"
		},
		{
			"fieldType":"empty",
			"rowspan":0,
			"colspan":0,
			"rowIndex":10,
			"colIndex":1,
			"uuid":"w2198a23ecac47f0",
			"belong":"left"
		},
		{
			"label":"实际到账金额",
			"fieldName":"actualReceivedAmt",
			"fieldType":"text",
			"dataType":"money(yuan)",
			"value":"",
			"placeholder":"请输入实际到账金额",
			"readOnly":false,
			"disabled":false,
			"isShow":true,
			"rules":[
				{
					"type":"required",
					"message":"实际到账金额不能为空",
					"trigger":"blur"
				}
			],
			"events":[],
			"colspan":2,
			"rowspan":1,
			"colIndex":0,
			"rowIndex":11,
			"state":[],
			"useState":"",
			"menuType":"common",
			"showContents":1,
			"href":{
				"path":"",
				"query":"",
				"callbackType":""
			},
			"isHref":false,
			"optBtn":[],
			"suffix":"元",
			"maxlength":"",
			"show-word-limit":false,
			"desensitization":"",
			"desensitizationFront":"",
			"desensitizationAfter":"",
			"isBigAmt":true,
			"uuid":"w028083545be4db8"
		},
		{
			"fieldType":"empty",
			"rowspan":0,
			"colspan":0,
			"rowIndex":11,
			"colIndex":1,
			"uuid":"wdd5a8b48399406f",
			"belong":"left"
		},
		{
			"label":"应退费金额",
			"fieldName":"refundAmt",
			"fieldType":"text",
			"dataType":"money(yuan)",
			"value":"",
			"placeholder":"请输入应退费金额",
			"readOnly":false,
			"disabled":false,
			"isShow":true,
			"rules":[],
			"events":[],
			"colspan":2,
			"rowspan":1,
			"colIndex":0,
			"rowIndex":12,
			"state":[],
			"useState":"",
			"menuType":"common",
			"showContents":1,
			"href":{
				"path":"",
				"query":"",
				"callbackType":""
			},
			"isHref":false,
			"optBtn":[],
			"suffix":"元",
			"maxlength":"",
			"show-word-limit":false,
			"desensitization":"",
			"desensitizationFront":"",
			"desensitizationAfter":"",
			"isBigAmt":true,
			"uuid":"wfcea803dea74490"
		},
		{
			"colspan":0,
			"showContents":1,
			"rowspan":0,
			"colIndex":1,
			"rowIndex":12,
			"state":[],
			"fieldType":"empty",
			"uuid":"w4b85969d789465a",
			"belong":"left"
		},
		{
			"label":"到账日期",
			"fieldName":"collectDate",
			"fieldType":"date",
			"dataType":"",
			"value":"",
			"placeholder":"请输入到账日期",
			"readOnly":false,
			"disabled":false,
			"isShow":true,
			"rules":[
				{
					"trigger":"change",
					"type":"required",
					"message":"到账日期不能为空"
				}
			],
			"events":[],
			"colspan":1,
			"rowspan":1,
			"colIndex":0,
			"rowIndex":13,
			"state":[],
			"useState":"",
			"menuType":"common",
			"showContents":1,
			"href":{
				"path":"",
				"query":"",
				"callbackType":""
			},
			"isHref":false,
			"optBtn":[],
			"dateFormat":{
				"format":"yyyy-MM-dd",
				"valueFormat":"yyyy-MM-dd"
			},
			"dateOption":{
				"isLong":false
			},
			"dateType":"date",
			"uuid":"wceedadb008c4ff0"
		},
		{
			"colspan":1,
			"showContents":1,
			"rowspan":1,
			"colIndex":1,
			"rowIndex":13,
			"state":[],
			"fieldType":"empty",
			"uuid":"w1f058ff83a5494c"
		},
		{
			"label":"到账账号",
			"fieldName":"receviedAccout",
			"fieldType":"text",
			"dataType":"String",
			"value":"",
			"placeholder":"请输入到账账号",
			"readOnly":false,
			"disabled":false,
			"isShow":true,
			"rules":[],
			"events":[
				{
					"callback":"bankInit",
					"type":"click"
				}
			],
			"colspan":1,
			"rowspan":1,
			"colIndex":0,
			"rowIndex":14,
			"state":[],
			"useState":"",
			"menuType":"common",
			"showContents":1,
			"href":{
				"path":"",
				"query":"",
				"callbackType":""
			},
			"isHref":false,
			"optBtn":[],
			"suffix":"",
			"maxlength":"",
			"show-word-limit":false,
			"desensitization":"",
			"desensitizationFront":"",
			"desensitizationAfter":"",
			"isBigAmt":false,
			"uuid":"w8bbbb89088c4c2e"
		},
		{
			"label":"到账账号开户行",
			"fieldName":"receviedBankName",
			"fieldType":"text",
			"dataType":"String",
			"value":"",
			"placeholder":"请输入到账账号开户行",
			"readOnly":false,
			"disabled":false,
			"isShow":true,
			"rules":[],
			"events":[],
			"colspan":1,
			"rowspan":1,
			"colIndex":1,
			"rowIndex":14,
			"state":[],
			"useState":"",
			"menuType":"common",
			"showContents":1,
			"href":{
				"path":"",
				"query":"",
				"callbackType":""
			},
			"isHref":false,
			"optBtn":[],
			"suffix":"",
			"maxlength":"",
			"show-word-limit":false,
			"desensitization":"",
			"desensitizationFront":"",
			"desensitizationAfter":"",
			"isBigAmt":false,
			"uuid":"wcedbb3815b2435c"
		},
		{
			"label":"到账账号户名",
			"fieldName":"receviedAccoutName",
			"fieldType":"text",
			"dataType":"String",
			"value":"",
			"placeholder":"请输入到账账号户名",
			"readOnly":false,
			"disabled":false,
			"isShow":true,
			"rules":[],
			"events":[],
			"colspan":1,
			"rowspan":1,
			"colIndex":0,
			"rowIndex":15,
			"state":[],
			"useState":"",
			"menuType":"common",
			"showContents":1,
			"href":{
				"path":"",
				"query":"",
				"callbackType":""
			},
			"isHref":false,
			"optBtn":[],
			"suffix":"",
			"maxlength":"",
			"show-word-limit":false,
			"desensitization":"",
			"desensitizationFront":"",
			"desensitizationAfter":"",
			"isBigAmt":false,
			"uuid":"wc9488ed1f814dfd"
		},
		{
			"colspan":1,
			"showContents":1,
			"rowspan":1,
			"colIndex":1,
			"rowIndex":15,
			"state":[],
			"fieldType":"empty",
			"uuid":"w4ad4968c8844fb5"
		},
		{
			"label":"备注",
			"fieldName":"remark",
			"fieldType":"textarea",
			"dataType":"String",
			"value":"",
			"placeholder":"请输入备注",
			"readOnly":false,
			"disabled":false,
			"isShow":true,
			"rules":[],
			"events":[],
			"colspan":2,
			"rowspan":1,
			"colIndex":0,
			"rowIndex":16,
			"state":[],
			"useState":"",
			"menuType":"common",
			"showContents":1,
			"href":{
				"path":"",
				"query":"",
				"callbackType":""
			},
			"isHref":false,
			"optBtn":[],
			"suffix":"",
			"maxlength":"500",
			"isAutoRows":false,
			"maxRows":6,
			"minRows":3,
			"show-word-limit":false,
			"desensitization":"",
			"desensitizationFront":"",
			"desensitizationAfter":"",
			"uuid":"w8bf48b8748c4289"
		},
		{
			"colspan":0,
			"showContents":1,
			"belong":"left",
			"rowspan":0,
			"colIndex":1,
			"rowIndex":16,
			"state":[],
			"fieldType":"empty",
			"uuid":"w4165b4433ac4ae2"
		},
		{
			"label":"主键Id",
			"fieldName":"collectId",
			"fieldType":"text",
			"dataType":"String",
			"value":"",
			"placeholder":"请输入主键Id",
			"readOnly":false,
			"disabled":true,
			"isShow":false,
			"rules":[
				{
					"trigger":"blur",
					"type":"required",
					"message":"主键Id不能为空"
				}
			],
			"events":[],
			"colspan":1,
			"rowspan":1,
			"colIndex":0,
			"rowIndex":0,
			"state":[],
			"useState":"",
			"menuType":"common",
			"showContents":1,
			"href":{
				"path":"",
				"query":"",
				"callbackType":""
			},
			"isHref":false,
			"optBtn":[],
			"suffix":"",
			"maxlength":"",
			"show-word-limit":false,
			"desensitization":"",
			"desensitizationFront":"",
			"desensitizationAfter":"",
			"isBigAmt":false,
			"uuid":"wfd3da990a82458e"
		},
		{
			"label":"缴款id",
			"fieldName":"chargeId",
			"fieldType":"text",
			"dataType":"String",
			"value":"",
			"placeholder":"请输入缴款id",
			"readOnly":false,
			"disabled":false,
			"isShow":false,
			"rules":[
				{
					"trigger":"blur",
					"type":"required",
					"message":"缴款id不能为空"
				}
			],
			"events":[],
			"colspan":1,
			"rowspan":1,
			"colIndex":1,
			"rowIndex":0,
			"state":[],
			"useState":"",
			"menuType":"common",
			"showContents":1,
			"href":{
				"path":"",
				"query":"",
				"callbackType":""
			},
			"isHref":false,
			"optBtn":[],
			"suffix":"",
			"maxlength":"",
			"show-word-limit":false,
			"desensitization":"",
			"desensitizationFront":"",
			"desensitizationAfter":"",
			"isBigAmt":false,
			"uuid":"w5a32a5f25904614"
		},
		{
			"label":"申请号",
			"fieldName":"applyId",
			"fieldType":"text",
			"dataType":"String",
			"value":"",
			"placeholder":"请输入申请号",
			"readOnly":false,
			"disabled":false,
			"isShow":false,
			"rules":[
				{
					"trigger":"blur",
					"type":"required",
					"message":"申请号不能为空"
				}
			],
			"events":[],
			"colspan":1,
			"rowspan":1,
			"colIndex":0,
			"rowIndex":0,
			"state":[],
			"useState":"",
			"menuType":"common",
			"showContents":1,
			"href":{
				"path":"",
				"query":"",
				"callbackType":""
			},
			"isHref":false,
			"optBtn":[],
			"suffix":"",
			"maxlength":"",
			"show-word-limit":false,
			"desensitization":"",
			"desensitizationFront":"",
			"desensitizationAfter":"",
			"isBigAmt":false,
			"uuid":"w905f8f3498c48ab"
		},
		{
			"label":"到账账户关联id",
			"fieldName":"receivedAccId",
			"fieldType":"text",
			"dataType":"String",
			"value":"",
			"placeholder":"请输入到账账户关联id",
			"readOnly":false,
			"disabled":false,
			"isShow":false,
			"rules":[
				{
					"trigger":"blur",
					"type":"required",
					"message":"到账账户关联id不能为空"
				}
			],
			"events":[],
			"colspan":1,
			"rowspan":1,
			"colIndex":1,
			"rowIndex":8,
			"state":[],
			"useState":"",
			"menuType":"common",
			"showContents":1,
			"href":{
				"path":"",
				"query":"",
				"callbackType":""
			},
			"isHref":false,
			"optBtn":[],
			"suffix":"",
			"maxlength":"",
			"show-word-limit":false,
			"desensitization":"",
			"desensitizationFront":"",
			"desensitizationAfter":"",
			"isBigAmt":false,
			"uuid":"w9c3d83c9fa84503"
		},
		{
			"label":"开票ID",
			"fieldName":"taxpayerId",
			"fieldType":"text",
			"dataType":"String",
			"value":"",
			"placeholder":"请输入开票ID",
			"readOnly":false,
			"disabled":false,
			"isShow":false,
			"rules":[
				{
					"trigger":"blur",
					"type":"required",
					"message":"开票ID不能为空"
				}
			],
			"events":[],
			"colspan":1,
			"rowspan":1,
			"colIndex":0,
			"rowIndex":8,
			"state":[],
			"useState":"",
			"menuType":"common",
			"showContents":1,
			"href":{
				"path":"",
				"query":"",
				"callbackType":""
			},
			"isHref":false,
			"optBtn":[],
			"suffix":"",
			"maxlength":"",
			"show-word-limit":false,
			"desensitization":"",
			"desensitizationFront":"",
			"desensitizationAfter":"",
			"isBigAmt":false,
			"uuid":"w7fe4843739e45b3"
		},
		{
			"label":"collectType",
			"fieldName":"collectType",
			"fieldType":"text",
			"dataType":"",
			"value":"",
			"placeholder":"请输入",
			"readOnly":false,
			"disabled":false,
			"isShow":false,
			"rules":[],
			"events":[],
			"colspan":1,
			"rowspan":1,
			"colIndex":"",
			"rowIndex":"",
			"state":[],
			"useState":"",
			"menuType":"common",
			"showContents":1,
			"href":{
				"path":"",
				"query":"",
				"callbackType":""
			},
			"isHref":false,
			"optBtn":[],
			"suffix":"",
			"maxlength":"",
			"show-word-limit":false,
			"desensitization":"",
			"desensitizationFront":"",
			"desensitizationAfter":"",
			"isBigAmt":false
		},
		{
			"label":"期号",
			"fieldName":"termNum",
			"fieldType":"text",
			"dataType":"int",
			"value":"",
			"placeholder":"请输入",
			"readOnly":false,
			"disabled":false,
			"isShow":false,
			"rules":[],
			"events":[],
			"colspan":1,
			"rowspan":1,
			"colIndex":0,
			"rowIndex":12,
			"state":[],
			"useState":"",
			"menuType":"common",
			"showContents":1,
			"href":{
				"path":"",
				"query":"",
				"callbackType":""
			},
			"isHref":false,
			"optBtn":[],
			"suffix":"",
			"maxlength":"",
			"show-word-limit":false,
			"desensitization":"",
			"desensitizationFront":"",
			"desensitizationAfter":"",
			"isBigAmt":false,
			"uuid":"w519c8e606b64800"
		}
	],
	"labelPosition":"right",
	"columns":2,
	"formName":"guaranteeCollectConfirmUpdateForm",
	"query":"null",
	"formDisabled":false
}